eeeCalc/__init__.py
eeeCalc/dBtoRatio.py
eeeCalc/filter.py
eeeCalc/general.py
eeeCalc/phasors.py
eeeCalc/secondDegreeDiffEq.py
eeeCalc/signalFunctions.py
eeeCalc/transferFunctionPlot.py
eeeCalc/.idea/.gitignore
eeeCalc/.idea/eeeCalc.iml
eeeCalc/.idea/misc.xml
eeeCalc/.idea/modules.xml
eeeCalc/.idea/workspace.xml
eeeCalc/.idea/inspectionProfiles/profiles_settings.xml
eeecalc-0.1.1.dist-info/METADATA
eeecalc-0.1.1.dist-info/WHEEL
eeecalc-0.1.1.dist-info/licenses/LICENSE
eeecalc-0.1.1.dist-info/RECORD
