Metadata-Version: 2.1
Name: eeeCalc
Version: 0.1.1
Summary: Package to aid electrical engineering calculations
Author-email: Kevin Johnson <john2003.kjj@gmail.com>
License-File: LICENSE
Classifier: License :: OSI Approved :: MIT License
Classifier: Operating System :: OS Independent
Classifier: Programming Language :: Python :: 3
Requires-Python: >=3.8
